apolloMusicPlayer/__init__.py
apolloMusicPlayer/customplayer.py
apolloMusicPlayer/testPlayer.py
apolloMusicPlayer-0.2.dist-info/DESCRIPTION.rst
apolloMusicPlayer-0.2.dist-info/METADATA
apolloMusicPlayer-0.2.dist-info/RECORD
apolloMusicPlayer-0.2.dist-info/WHEEL
apolloMusicPlayer-0.2.dist-info/metadata.json
apolloMusicPlayer-0.2.dist-info/top_level.txt
