Metadata-Version: 2.0
Name: apolloMusicPlayer
Version: 0.2
Summary: The music player for Apollo
Home-page: https://github.com/ebber/apolloMusicPlayer
Author: Erik Beitel
Author-email: erik.beitel@gmail.com
License: UNKNOWN
Download-URL: https://github.com/ebber/apolloMusicPlayer/archive/0.2.tar.gz
Keywords: audio,music player
Platform: UNKNOWN
Requires-Dist: logging
Requires-Dist: musicplayer
